collectd_cvmfs/__init__.py
usr/share/collectd/collectd_cvmfs.db
collectd_cvmfs-1.3.4.dist-info/LICENSE
collectd_cvmfs-1.3.4.dist-info/METADATA
collectd_cvmfs-1.3.4.dist-info/WHEEL
collectd_cvmfs-1.3.4.dist-info/top_level.txt
collectd_cvmfs-1.3.4.dist-info/RECORD
