Metadata-Version: 2.2
Name: collectd_cvmfs
Version: 1.3.4
Summary: Collectd Plugin to Monitor CvmFS Clients
Home-page: https://github.com/cvmfs/collectd-cvmfs
Author: Luis Fenandez Alvarez
Author-email: luis.fernandez.alvarez@cern.ch
License: Apache II
Keywords: collectd cvmfs monitoring
Classifier: Development Status :: 4 - Beta
Classifier: Intended Audience :: System Administrators
Classifier: Operating System :: POSIX :: Linux
Classifier: Programming Language :: Python
Classifier: Topic :: System :: Monitoring
License-File: LICENSE
Requires-Dist: pyxattr
Requires-Dist: psutil
Requires-Dist: scandir; python_version < "3.5"
Dynamic: author
Dynamic: author-email
Dynamic: classifier
Dynamic: description
Dynamic: description-content-type
Dynamic: home-page
Dynamic: keywords
Dynamic: license
Dynamic: requires-dist
Dynamic: summary
